{
    "last_updated": "2026-04-24 06:21:54 UTC",
    "countries": {
        "us": 1500,
        "ir": 1500,
        "bz": 73,
        "de": 1500,
        "al": 19,
        "ca": 1500,
        "unknown": 1500,
        "fr": 727,
        "nl": 935,
        "vn": 395,
        "tw": 158,
        "jp": 208,
        "gb": 793,
        "ru": 405,
        "sg": 346,
        "it": 51,
        "cw": 31,
        "hk": 442,
        "au": 37,
        "es": 47,
        "pl": 137,
        "se": 154,
        "bg": 44,
        "fi": 114,
        "ch": 54,
        "dk": 11,
        "kz": 60,
        "cy": 87,
        "at": 31,
        "br": 43,
        "cz": 43,
        "kr": 207,
        "cn": 161,
        "in": 103,
        "hr": 8,
        "pr": 2,
        "pa": 13,
        "pk": 31,
        "th": 5,
        "lu": 8,
        "ua": 62,
        "hu": 22,
        "vg": 7,
        "nz": 7,
        "za": 49,
        "lv": 62,
        "tr": 93,
        "ec": 4,
        "co": 8,
        "ie": 21,
        "cr": 50,
        "gr": 5,
        "no": 9,
        "be": 19,
        "ee": 38,
        "bh": 15,
        "my": 25,
        "ar": 17,
        "pe": 10,
        "sc": 13,
        "id": 29,
        "bo": 9,
        "mk": 6,
        "ma": 13,
        "cl": 15,
        "lt": 29,
        "ae": 28,
        "mx": 8,
        "pt": 25,
        "az": 12,
        "il": 6,
        "kh": 6,
        "rs": 8,
        "am": 10,
        "sa": 4,
        "si": 5,
        "mo": 6,
        "mt": 9,
        "py": 3,
        "ro": 10,
        "is": 4,
        "ba": 8,
        "im": 3,
        "md": 4,
        "li": 5,
        "sk": 2,
        "jo": 3,
        "om": 2,
        "eg": 4,
        "ph": 2,
        "mn": 1,
        "ng": 1
    }
}