{
    "last_updated": "2026-06-25 18:25:36 UTC",
    "countries": {
        "us": 1500,
        "za": 53,
        "unknown": 1500,
        "es": 127,
        "ir": 1500,
        "nl": 1367,
        "ru": 603,
        "fi": 300,
        "de": 1500,
        "hu": 30,
        "hk": 483,
        "vn": 48,
        "fr": 798,
        "th": 40,
        "ca": 1500,
        "jp": 336,
        "gb": 734,
        "se": 318,
        "pl": 198,
        "tw": 96,
        "kz": 40,
        "ie": 70,
        "it": 353,
        "lt": 198,
        "kr": 162,
        "au": 86,
        "lv": 113,
        "sg": 280,
        "sc": 401,
        "be": 21,
        "tr": 194,
        "ua": 28,
        "lu": 10,
        "no": 9,
        "ae": 71,
        "al": 21,
        "md": 14,
        "mx": 3,
        "ch": 183,
        "in": 98,
        "br": 31,
        "nz": 9,
        "cy": 71,
        "cn": 139,
        "at": 51,
        "id": 41,
        "bz": 48,
        "ge": 14,
        "is": 13,
        "my": 28,
        "jm": 1,
        "vg": 3,
        "ph": 10,
        "am": 11,
        "ro": 25,
        "cr": 34,
        "pt": 11,
        "cl": 8,
        "rs": 10,
        "az": 9,
        "sa": 5,
        "li": 2,
        "cw": 17,
        "sk": 3,
        "dk": 6,
        "cz": 23,
        "pe": 5,
        "ar": 6,
        "bg": 11,
        "co": 3,
        "pk": 2,
        "mk": 3,
        "hr": 2,
        "ee": 15,
        "il": 6,
        "mo": 6,
        "ba": 5,
        "gr": 4,
        "im": 3,
        "mn": 2,
        "ng": 1,
        "pa": 1,
        "si": 2,
        "iq": 1,
        "by": 1,
        "kw": 1,
        "kg": 1
    }
}