{
    "last_updated": "2026-04-15 03:35:31 UTC",
    "countries": {
        "us": 1500,
        "unknown": 1500,
        "vn": 390,
        "ir": 1500,
        "nl": 786,
        "ca": 1500,
        "tw": 115,
        "ru": 274,
        "lv": 69,
        "it": 49,
        "sg": 334,
        "fr": 691,
        "hk": 398,
        "gb": 728,
        "cy": 79,
        "de": 906,
        "in": 94,
        "ae": 27,
        "ch": 51,
        "ie": 21,
        "cn": 158,
        "jp": 231,
        "bg": 37,
        "pa": 7,
        "jo": 3,
        "mx": 9,
        "tr": 67,
        "pl": 148,
        "au": 45,
        "bo": 8,
        "vg": 3,
        "se": 92,
        "at": 51,
        "kr": 89,
        "cr": 49,
        "md": 4,
        "kz": 44,
        "pr": 3,
        "id": 32,
        "cz": 32,
        "bz": 59,
        "lt": 23,
        "pk": 26,
        "ua": 57,
        "es": 33,
        "za": 27,
        "br": 25,
        "my": 32,
        "ar": 14,
        "fi": 99,
        "sc": 11,
        "hu": 35,
        "be": 24,
        "ee": 17,
        "no": 10,
        "dk": 15,
        "cw": 10,
        "lu": 8,
        "ma": 1,
        "bh": 5,
        "co": 6,
        "cl": 16,
        "ro": 13,
        "rs": 5,
        "sa": 9,
        "pt": 14,
        "am": 8,
        "gr": 9,
        "kh": 5,
        "al": 15,
        "hr": 9,
        "by": 2,
        "ec": 7,
        "eg": 4,
        "im": 3,
        "pe": 8,
        "is": 4,
        "ba": 9,
        "mk": 4,
        "mt": 7,
        "az": 10,
        "py": 2,
        "li": 5,
        "th": 7,
        "si": 4,
        "mo": 5,
        "sk": 1,
        "il": 8,
        "nz": 1,
        "ph": 3,
        "ng": 1
    }
}