{
    "last_updated": "2026-06-11 22:12:41 UTC",
    "countries": {
        "unknown": 1500,
        "ge": 20,
        "hk": 415,
        "ca": 1500,
        "nl": 1311,
        "ir": 1500,
        "ru": 542,
        "sc": 461,
        "fr": 909,
        "us": 1500,
        "gb": 621,
        "vn": 35,
        "it": 250,
        "be": 29,
        "za": 18,
        "de": 1500,
        "at": 61,
        "tr": 121,
        "jp": 271,
        "cy": 80,
        "ie": 37,
        "pl": 208,
        "cn": 137,
        "ch": 209,
        "cz": 38,
        "mx": 17,
        "gr": 4,
        "es": 82,
        "no": 11,
        "se": 113,
        "sg": 344,
        "kz": 22,
        "kr": 137,
        "lv": 54,
        "tw": 96,
        "fi": 103,
        "in": 53,
        "rs": 14,
        "ph": 5,
        "ee": 14,
        "bz": 61,
        "dk": 24,
        "cr": 35,
        "lt": 23,
        "au": 49,
        "ar": 5,
        "my": 37,
        "lu": 8,
        "br": 21,
        "ae": 22,
        "th": 28,
        "nz": 10,
        "sa": 2,
        "az": 13,
        "cl": 15,
        "mo": 6,
        "ua": 6,
        "cw": 2,
        "id": 12,
        "iq": 16,
        "md": 3,
        "hu": 5,
        "bg": 12,
        "pa": 1,
        "is": 10,
        "ro": 25,
        "ng": 1,
        "kg": 2,
        "im": 3,
        "co": 8,
        "vg": 3,
        "al": 13,
        "li": 2,
        "ba": 5,
        "il": 8,
        "am": 1,
        "pt": 8,
        "pe": 2,
        "si": 2,
        "mk": 3,
        "hr": 2,
        "sk": 1,
        "pr": 1,
        "mn": 1
    }
}