{
    "last_updated": "2026-04-16 21:03:41 UTC",
    "countries": {
        "ir": 1500,
        "fr": 725,
        "de": 980,
        "ca": 1500,
        "hk": 432,
        "unknown": 1500,
        "vn": 381,
        "nl": 840,
        "us": 1500,
        "gb": 742,
        "cy": 89,
        "sg": 330,
        "tw": 128,
        "bo": 8,
        "pl": 147,
        "cn": 158,
        "ru": 252,
        "ch": 52,
        "im": 3,
        "bz": 64,
        "cl": 10,
        "tr": 61,
        "ec": 3,
        "py": 2,
        "br": 28,
        "my": 30,
        "es": 35,
        "hu": 45,
        "id": 32,
        "no": 6,
        "se": 101,
        "lv": 87,
        "ua": 54,
        "jp": 246,
        "fi": 102,
        "za": 26,
        "at": 52,
        "in": 95,
        "ae": 21,
        "mt": 8,
        "it": 74,
        "mo": 6,
        "be": 21,
        "kz": 40,
        "pt": 15,
        "cz": 30,
        "kr": 102,
        "pk": 23,
        "co": 6,
        "lt": 24,
        "dk": 15,
        "au": 30,
        "ar": 14,
        "sa": 4,
        "cr": 54,
        "al": 14,
        "bg": 43,
        "gr": 9,
        "az": 12,
        "lu": 8,
        "th": 10,
        "is": 6,
        "ee": 16,
        "kh": 6,
        "pa": 7,
        "cw": 10,
        "hr": 8,
        "ro": 9,
        "sc": 9,
        "pe": 7,
        "si": 4,
        "ie": 21,
        "ba": 8,
        "ma": 7,
        "bh": 12,
        "il": 8,
        "nz": 2,
        "am": 10,
        "mx": 6,
        "rs": 5,
        "ph": 2,
        "mn": 1,
        "jo": 3,
        "sk": 1,
        "li": 4,
        "mk": 5,
        "md": 4,
        "eg": 4,
        "pr": 4,
        "vg": 3,
        "ng": 1
    }
}