{
    "last_updated": "2026-05-21 21:48:16 UTC",
    "countries": {
        "ir": 1500,
        "unknown": 1500,
        "ca": 1500,
        "us": 1500,
        "se": 117,
        "ru": 517,
        "de": 1181,
        "fr": 718,
        "jp": 256,
        "nl": 1226,
        "pl": 298,
        "hk": 427,
        "kr": 140,
        "gb": 897,
        "bg": 38,
        "cz": 49,
        "vn": 655,
        "at": 40,
        "ae": 45,
        "au": 60,
        "sg": 294,
        "fi": 177,
        "tr": 90,
        "cn": 98,
        "ie": 38,
        "tw": 142,
        "am": 19,
        "lv": 60,
        "kz": 66,
        "mx": 7,
        "sa": 16,
        "th": 24,
        "br": 56,
        "al": 19,
        "my": 40,
        "bz": 90,
        "ua": 29,
        "kw": 13,
        "ec": 10,
        "cy": 81,
        "lt": 33,
        "pe": 10,
        "ee": 31,
        "in": 86,
        "pt": 25,
        "ch": 52,
        "za": 34,
        "hr": 10,
        "ma": 14,
        "mt": 7,
        "es": 39,
        "il": 15,
        "id": 14,
        "dk": 16,
        "bh": 15,
        "pa": 11,
        "vg": 7,
        "gr": 11,
        "cl": 11,
        "cw": 49,
        "ge": 2,
        "be": 26,
        "cr": 38,
        "ba": 4,
        "pk": 16,
        "eg": 4,
        "mk": 12,
        "it": 38,
        "ph": 1,
        "ro": 19,
        "sc": 14,
        "rs": 18,
        "jo": 14,
        "no": 4,
        "bo": 7,
        "md": 6,
        "sk": 1,
        "az": 16,
        "hu": 38,
        "lu": 9,
        "kh": 5,
        "im": 3,
        "nz": 4,
        "si": 5,
        "py": 2,
        "co": 3,
        "mo": 6,
        "is": 4,
        "pr": 2,
        "mn": 1,
        "li": 4,
        "ng": 1,
        "mm": 2
    }
}